{"packages/cupertino_icons/assets/CupertinoIcons.ttf":["packages/cupertino_icons/assets/CupertinoIcons.ttf"],"assets/avatar.jpg":["assets/avatar.jpg"],"assets/chplay.png":["assets/chplay.png"],"assets/cover.jpg":["assets/cover.jpg"],"assets/error404.png":["assets/error404.png"],"assets/facebook.png":["assets/facebook.png"],"assets/getapp.png":["assets/getapp.png"],"assets/github.png":["assets/github.png"],"assets/hvan.png":["assets/hvan.png"],"assets/hvapp.png":["assets/hvapp.png"],"assets/hvapple.png":["assets/hvapple.png"],"assets/hvbg1.png":["assets/hvbg1.png"],"assets/hvbg2.png":["assets/hvbg2.png"],"assets/hvlogo.png":["assets/hvlogo.png"],"assets/instagram.png":["assets/instagram.png"],"assets/twitter.png":["assets/twitter.png"],"assets/youtube.png":["assets/youtube.png"]}